probecon/__init__.py
probecon/probecon.py
probecon-0.1.dist-info/LICENSE
probecon-0.1.dist-info/METADATA
probecon-0.1.dist-info/WHEEL
probecon-0.1.dist-info/top_level.txt
probecon-0.1.dist-info/RECORD
